moonstreamapi/__init__.py
moonstreamapi/abi_decoder.py
moonstreamapi/actions.py
moonstreamapi/api.py
moonstreamapi/data.py
moonstreamapi/middleware.py
moonstreamapi/py.typed
moonstreamapi/reporter.py
moonstreamapi/selectors_storage.py
moonstreamapi/settings.py
moonstreamapi/stream_boundaries.py
moonstreamapi/stream_queries.py
moonstreamapi/test_actions_abi_validations.py
moonstreamapi/test_stream_boundaries.py
moonstreamapi/test_stream_queries.py
moonstreamapi/text_actions.py
moonstreamapi/version.py
moonstreamapi/web3_provider.py
moonstreamapi/admin/__init__.py
moonstreamapi/admin/cli.py
moonstreamapi/admin/moonworm_tasks.py
moonstreamapi/admin/queries.py
moonstreamapi/admin/subscription_types.py
moonstreamapi/admin/subscriptions.py
moonstreamapi/admin/usage.py
moonstreamapi/admin/migrations/__init__.py
moonstreamapi/admin/migrations/add_selectors.py
moonstreamapi/admin/migrations/checksum_address.py
moonstreamapi/admin/migrations/generate_entity_subscriptions.py
moonstreamapi/admin/migrations/update_dashboard_subscription_key.py
moonstreamapi/providers/__init__.py
moonstreamapi/providers/bugout.py
moonstreamapi/providers/moonworm_provider.py
moonstreamapi/providers/transactions.py
moonstreamapi/routes/__init__.py
moonstreamapi/routes/address_info.py
moonstreamapi/routes/dashboards.py
moonstreamapi/routes/queries.py
moonstreamapi/routes/streams.py
moonstreamapi/routes/subscriptions.py
moonstreamapi/routes/txinfo.py
moonstreamapi/routes/users.py
moonstreamapi/routes/whales.py
moonstreamapi-0.4.11.dist-info/METADATA
moonstreamapi-0.4.11.dist-info/WHEEL
moonstreamapi-0.4.11.dist-info/entry_points.txt
moonstreamapi-0.4.11.dist-info/top_level.txt
moonstreamapi-0.4.11.dist-info/RECORD
