Metadata-Version: 2.1
Name: moonstreamapi
Version: 0.4.11
Summary: The Bugout blockchain inspector API.
Home-page: https://github.com/bugout-dev/moonstream
Author: Bugout.dev
Author-email: engineering@bugout.dev
Classifier: Development Status :: 3 - Alpha
Classifier: Programming Language :: Python
Classifier: License :: OSI Approved :: Apache Software License
Classifier: Topic :: Software Development :: Libraries
Requires-Dist: appdirs
Requires-Dist: boto3
Requires-Dist: bugout >=0.2.15
Requires-Dist: fastapi
Requires-Dist: moonstream >=0.1.2
Requires-Dist: moonstreamdb >=0.4.6
Requires-Dist: moonstreamdb-v3 >=0.1.3
Requires-Dist: humbug
Requires-Dist: pydantic ==1.10.2
Requires-Dist: pyevmasm
Requires-Dist: python-dateutil
Requires-Dist: python-multipart
Requires-Dist: python-slugify
Requires-Dist: uvicorn
Requires-Dist: web3 <6,>=5.30.0
Provides-Extra: dev
Requires-Dist: black ; extra == 'dev'
Requires-Dist: isort ; extra == 'dev'
Requires-Dist: mypy ; extra == 'dev'
Requires-Dist: types-requests ; extra == 'dev'
Requires-Dist: types-python-dateutil ; extra == 'dev'
Provides-Extra: distribute
Requires-Dist: build ; extra == 'distribute'
Requires-Dist: twine ; extra == 'distribute'
